LICENSE
MANIFEST.in
README.md
setup.cfg
setup.py
tests/__init__.py
tests/test_templatetag.py
tests/test_app/__init__.py
tests/test_app/models.py
tests/test_app/settings.py
tests/test_app/urls.py
wagtail_lazyimages/__init__.py
wagtail_lazyimages.egg-info/PKG-INFO
wagtail_lazyimages.egg-info/SOURCES.txt
wagtail_lazyimages.egg-info/dependency_links.txt
wagtail_lazyimages.egg-info/top_level.txt
wagtail_lazyimages/templatetags/__init__.py
wagtail_lazyimages/templatetags/lazyimages_tags.py