Metadata-Version: 2.1
Name: wagtail-lazyimages
Version: 0.1.3
Summary: A wagtail plugin that generates tiny blurry placeholder images for lazy-loading.
Home-page: https://github.com/ptrck/wagtail-lazyimages/
Author: Patrick Dengler
Author-email: info@patrickdengler.de
License: BSD License
Platform: UNKNOWN
Classifier: Environment :: Web Environment
Classifier: Framework :: Django
Classifier: Framework :: Wagtail
Classifier: Intended Audience :: Developers
Classifier: License :: OSI Approved :: BSD License
Classifier: Operating System :: OS Independent
Classifier: Programming Language :: Python
Classifier: Programming Language :: Python :: 3.5
Classifier: Programming Language :: Python :: 3.6
Classifier: Topic :: Internet :: WWW/HTTP
Classifier: Topic :: Internet :: WWW/HTTP :: Dynamic Content
